Fishi/__init__.py
Fishi/database/__init__.py
Fishi/database/json.py
Fishi/database/mongodb.py
Fishi/model/__init__.py
Fishi/model/fisher_model.py
Fishi/model/preprocessing.py
Fishi/optimization/__init__.py
Fishi/optimization/caller.py
Fishi/optimization/display.py
Fishi/optimization/penalty.py
Fishi/optimization/scipy_global_optim.py
Fishi/plotting/__init__.py
Fishi/plotting/plotting.py
Fishi/solving/__init__.py
Fishi/solving/criteria.py
Fishi/solving/display.py
Fishi/solving/solve_fsm.py
fishi-0.1.1.dist-info/METADATA
fishi-0.1.1.dist-info/WHEEL
fishi-0.1.1.dist-info/licenses/LICENSE
fishi-0.1.1.dist-info/RECORD
