Metadata-Version: 2.1
Name: Fishi
Version: 0.1.1
Summary: Optimal experimental design utilizing the Fischer information matrix
Project-URL: Home-page, https://github.com/Spatial-Systems-Biology-Freiburg/Model-Design-Fischer-Information-Matrix
Project-URL: Bug Tracker, https://github.com/Spatial-Systems-Biology-Freiburg/Model-Design-Fischer-Information-Matrix/issues
Project-URL: Documentation, https://spatial-systems-biology-freiburg.github.io/Fishi/
Project-URL: Source code, https://github.com/Spatial-Systems-Biology-Freiburg/Fishi
Author-email: Jonas Pleyer <jonas.pleyer@fdm.uni-freiburg.de>, Polina Gaindrik <p.gaindrik@tsenso.com>
License-File: LICENSE
Classifier: License :: OSI Approved :: MIT License
Classifier: Operating System :: OS Independent
Classifier: Programming Language :: Python :: 3
Requires-Python: >=3.7
Requires-Dist: matplotlib
Requires-Dist: numpy
Requires-Dist: pydantic
Requires-Dist: pymongo
Requires-Dist: pytest
Requires-Dist: scipy
